{
    "73adb948-a7ed-4bdd-9bc6-9014e39ba330": {
        "date": "2023",
        "description": "The SF90 Stradale is the first ever Ferrari to feature PHEV (Plug-in Hybrid Electric Vehicle) architecture",
        "imageUrl": "https://upload.wikimedia.org/wikipedia/commons/1/13/Red_2019_Ferrari_SF90_Stradale_%2848264238897%29_%28cropped%29.jpg",
        "name": "Ferrari SF90 Stradale",
        "produced": "500",
        "type": "Hybrid",
        "_createdOn": 1765032669156,
        "_id": "73adb948-a7ed-4bdd-9bc6-9014e39ba330"
    }
}